LICENSE.TXT
README.md
setup.cfg
setup.py
src/__init__.py
src/abbers_without_classifier.py
src/calib_test.py
src/multiclass_one_vs_all.py
src/test_one_one.py
src/venn_abers.py
venn_abers.egg-info/PKG-INFO
venn_abers.egg-info/SOURCES.txt
venn_abers.egg-info/dependency_links.txt
venn_abers.egg-info/requires.txt
venn_abers.egg-info/top_level.txt